somtodaypython/__init__.py
somtodaypython/nonasyncsomtoday.py
somtodaypython-1.2.2.dist-info/licenses/LICENSE
somtodaypython-1.2.2.dist-info/METADATA
somtodaypython-1.2.2.dist-info/WHEEL
somtodaypython-1.2.2.dist-info/top_level.txt
somtodaypython-1.2.2.dist-info/RECORD
