Metadata-Version: 2.4
Name: somtodaypython
Version: 1.2.2
Summary: Python package for interacting & fetching somtoday's data.
Author-email: luxkatana <taseen.bibi@gmail.com>
License-Expression: MIT
Project-URL: Homepage, https://github.com/luxkatana/somtodayapi_python
Project-URL: Issues, https://github.com/luxkatana/somtodayapi_python/issues
Project-URL: Repository, https://github.com/luxkatana/somtodayapi_python.git
Keywords: api,somtoday,SOMtoday,python,somtodaypython
Requires-Python: >=3.9
License-File: LICENSE
Dynamic: license-file
